<annotation>
	<folder>collection1_annotations</folder>
	<filename>1260724486963257346_0.jpg</filename>
	<path>C:\Users\Alperen\Desktop\collection_initial\collection1_annotations\1260724486963257346_0.jpg</path>
	<source>
		<database>Unknown</database>
	</source>
	<size>
		<width>675</width>
		<height>1200</height>
		<depth>3</depth>
	</size>
	<segmented>0</segmented>
	<object>
		<name>mask</name>
		<pose>Unspecified</pose>
		<truncated>0</truncated>
		<difficult>0</difficult>
		<bndbox>
			<xmin>34</xmin>
			<ymin>384</ymin>
			<xmax>225</xmax>
			<ymax>627</ymax>
		</bndbox>
	</object>
	<object>
		<name>mask</name>
		<pose>Unspecified</pose>
		<truncated>1</truncated>
		<difficult>0</difficult>
		<bndbox>
			<xmin>437</xmin>
			<ymin>479</ymin>
			<xmax>675</xmax>
			<ymax>839</ymax>
		</bndbox>
	</object>
</annotation>
