<annotation>
	<folder>collection1_annotations</folder>
	<filename>1261831926240800768_0.jpg</filename>
	<path>C:\Users\Alperen\Desktop\collection_initial\collection1_annotations\1261831926240800768_0.jpg</path>
	<source>
		<database>Unknown</database>
	</source>
	<size>
		<width>828</width>
		<height>1072</height>
		<depth>3</depth>
	</size>
	<segmented>0</segmented>
	<object>
		<name>mask</name>
		<pose>Unspecified</pose>
		<truncated>0</truncated>
		<difficult>0</difficult>
		<bndbox>
			<xmin>244</xmin>
			<ymin>256</ymin>
			<xmax>508</xmax>
			<ymax>595</ymax>
		</bndbox>
	</object>
</annotation>
