<annotation>
	<folder>collection1_annotations</folder>
	<filename>1261500951791198209_0.jpg</filename>
	<path>C:\Users\Alperen\Desktop\collection_initial\collection1_annotations\1261500951791198209_0.jpg</path>
	<source>
		<database>Unknown</database>
	</source>
	<size>
		<width>675</width>
		<height>1200</height>
		<depth>3</depth>
	</size>
	<segmented>0</segmented>
	<object>
		<name>mask</name>
		<pose>Unspecified</pose>
		<truncated>0</truncated>
		<difficult>0</difficult>
		<bndbox>
			<xmin>162</xmin>
			<ymin>664</ymin>
			<xmax>197</xmax>
			<ymax>709</ymax>
		</bndbox>
	</object>
	<object>
		<name>mask</name>
		<pose>Unspecified</pose>
		<truncated>0</truncated>
		<difficult>0</difficult>
		<bndbox>
			<xmin>512</xmin>
			<ymin>603</ymin>
			<xmax>557</xmax>
			<ymax>660</ymax>
		</bndbox>
	</object>
	<object>
		<name>mask</name>
		<pose>Unspecified</pose>
		<truncated>0</truncated>
		<difficult>0</difficult>
		<bndbox>
			<xmin>458</xmin>
			<ymin>277</ymin>
			<xmax>503</xmax>
			<ymax>340</ymax>
		</bndbox>
	</object>
	<object>
		<name>no mask</name>
		<pose>Unspecified</pose>
		<truncated>0</truncated>
		<difficult>0</difficult>
		<bndbox>
			<xmin>338</xmin>
			<ymin>622</ymin>
			<xmax>382</xmax>
			<ymax>679</ymax>
		</bndbox>
	</object>
	<object>
		<name>no mask</name>
		<pose>Unspecified</pose>
		<truncated>0</truncated>
		<difficult>0</difficult>
		<bndbox>
			<xmin>296</xmin>
			<ymin>293</ymin>
			<xmax>342</xmax>
			<ymax>353</ymax>
		</bndbox>
	</object>
</annotation>
