<annotation>
	<folder>collection1_annotations</folder>
	<filename>1261357561959202825_2.jpg</filename>
	<path>C:\Users\Alperen\Desktop\collection_initial\collection1_annotations\1261357561959202825_2.jpg</path>
	<source>
		<database>Unknown</database>
	</source>
	<size>
		<width>900</width>
		<height>1200</height>
		<depth>3</depth>
	</size>
	<segmented>0</segmented>
	<object>
		<name>mask</name>
		<pose>Unspecified</pose>
		<truncated>0</truncated>
		<difficult>0</difficult>
		<bndbox>
			<xmin>267</xmin>
			<ymin>502</ymin>
			<xmax>301</xmax>
			<ymax>551</ymax>
		</bndbox>
	</object>
	<object>
		<name>mask</name>
		<pose>Unspecified</pose>
		<truncated>0</truncated>
		<difficult>0</difficult>
		<bndbox>
			<xmin>410</xmin>
			<ymin>571</ymin>
			<xmax>482</xmax>
			<ymax>669</ymax>
		</bndbox>
	</object>
</annotation>
