<annotation verified="yes">
	<folder>collection1_annotations</folder>
	<filename>1261804887077076993_2.jpg</filename>
	<path>C:\Users\Alperen\Desktop\collection_initial\collection1_annotations\1261804887077076993_2.jpg</path>
	<source>
		<database>Unknown</database>
	</source>
	<size>
		<width>900</width>
		<height>1200</height>
		<depth>3</depth>
	</size>
	<segmented>0</segmented>
	<object>
		<name>mask</name>
		<pose>Unspecified</pose>
		<truncated>0</truncated>
		<difficult>0</difficult>
		<bndbox>
			<xmin>459</xmin>
			<ymin>509</ymin>
			<xmax>492</xmax>
			<ymax>560</ymax>
		</bndbox>
	</object>
	<object>
		<name>mask</name>
		<pose>Unspecified</pose>
		<truncated>0</truncated>
		<difficult>1</difficult>
		<bndbox>
			<xmin>269</xmin>
			<ymin>533</ymin>
			<xmax>280</xmax>
			<ymax>548</ymax>
		</bndbox>
	</object>
	<object>
		<name>mask</name>
		<pose>Unspecified</pose>
		<truncated>0</truncated>
		<difficult>1</difficult>
		<bndbox>
			<xmin>301</xmin>
			<ymin>532</ymin>
			<xmax>314</xmax>
			<ymax>545</ymax>
		</bndbox>
	</object>
</annotation>
