<annotation verified="yes">
	<folder>collection1_annotations</folder>
	<filename>1261390875520729088_0.jpg</filename>
	<path>C:\Users\Alperen\Desktop\collection_initial\collection1_annotations\1261390875520729088_0.jpg</path>
	<source>
		<database>Unknown</database>
	</source>
	<size>
		<width>675</width>
		<height>1200</height>
		<depth>3</depth>
	</size>
	<segmented>0</segmented>
	<object>
		<name>mask</name>
		<pose>Unspecified</pose>
		<truncated>0</truncated>
		<difficult>0</difficult>
		<bndbox>
			<xmin>366</xmin>
			<ymin>364</ymin>
			<xmax>417</xmax>
			<ymax>434</ymax>
		</bndbox>
	</object>
	<object>
		<name>mask</name>
		<pose>Unspecified</pose>
		<truncated>0</truncated>
		<difficult>0</difficult>
		<bndbox>
			<xmin>237</xmin>
			<ymin>429</ymin>
			<xmax>285</xmax>
			<ymax>501</ymax>
		</bndbox>
	</object>
</annotation>
