<annotation>
	<folder>collection1_annotations</folder>
	<filename>1262263723428700162_0.jpg</filename>
	<path>C:\Users\Alperen\Desktop\collection_initial\collection1_annotations\1262263723428700162_0.jpg</path>
	<source>
		<database>Unknown</database>
	</source>
	<size>
		<width>1080</width>
		<height>1074</height>
		<depth>3</depth>
	</size>
	<segmented>0</segmented>
	<object>
		<name>no mask</name>
		<pose>Unspecified</pose>
		<truncated>0</truncated>
		<difficult>0</difficult>
		<bndbox>
			<xmin>883</xmin>
			<ymin>64</ymin>
			<xmax>1009</xmax>
			<ymax>243</ymax>
		</bndbox>
	</object>
	<object>
		<name>no mask</name>
		<pose>Unspecified</pose>
		<truncated>0</truncated>
		<difficult>0</difficult>
		<bndbox>
			<xmin>453</xmin>
			<ymin>83</ymin>
			<xmax>615</xmax>
			<ymax>309</ymax>
		</bndbox>
	</object>
</annotation>
