<annotation>
	<folder>collection_new_berat</folder>
	<filename>1265166710216077312_2.jpg</filename>
	<path>C:\Users\Alperen\Desktop\collection_new_berat\1265166710216077312_2.jpg</path>
	<source>
		<database>Unknown</database>
	</source>
	<size>
		<width>694</width>
		<height>555</height>
		<depth>3</depth>
	</size>
	<segmented>0</segmented>
	<object>
		<name>mask</name>
		<pose>Unspecified</pose>
		<truncated>0</truncated>
		<difficult>0</difficult>
		<bndbox>
			<xmin>613</xmin>
			<ymin>161</ymin>
			<xmax>666</xmax>
			<ymax>228</ymax>
		</bndbox>
	</object>
	<object>
		<name>mask</name>
		<pose>Unspecified</pose>
		<truncated>0</truncated>
		<difficult>0</difficult>
		<bndbox>
			<xmin>38</xmin>
			<ymin>183</ymin>
			<xmax>92</xmax>
			<ymax>240</ymax>
		</bndbox>
	</object>
	<object>
		<name>mask</name>
		<pose>Unspecified</pose>
		<truncated>0</truncated>
		<difficult>0</difficult>
		<bndbox>
			<xmin>447</xmin>
			<ymin>192</ymin>
			<xmax>482</xmax>
			<ymax>236</ymax>
		</bndbox>
	</object>
	<object>
		<name>mask</name>
		<pose>Unspecified</pose>
		<truncated>0</truncated>
		<difficult>0</difficult>
		<bndbox>
			<xmin>211</xmin>
			<ymin>178</ymin>
			<xmax>256</xmax>
			<ymax>236</ymax>
		</bndbox>
	</object>
	<object>
		<name>mask</name>
		<pose>Unspecified</pose>
		<truncated>0</truncated>
		<difficult>0</difficult>
		<bndbox>
			<xmin>315</xmin>
			<ymin>204</ymin>
			<xmax>356</xmax>
			<ymax>255</ymax>
		</bndbox>
	</object>
</annotation>
