<annotation>
	<folder>collection_new_annotations</folder>
	<filename>1271578797658144768_0.jpg</filename>
	<path>C:\Users\Alperen\Desktop\collection_new_annotations\1271578797658144768_0.jpg</path>
	<source>
		<database>Unknown</database>
	</source>
	<size>
		<width>1125</width>
		<height>1175</height>
		<depth>3</depth>
	</size>
	<segmented>0</segmented>
	<object>
		<name>mask</name>
		<pose>Unspecified</pose>
		<truncated>0</truncated>
		<difficult>0</difficult>
		<bndbox>
			<xmin>473</xmin>
			<ymin>97</ymin>
			<xmax>802</xmax>
			<ymax>580</ymax>
		</bndbox>
	</object>
</annotation>
