<annotation>
	<folder>Canada</folder>
	<filename>EagqdVXXkAEO4ZZ.jpg</filename>
	<path>C:\Users\Alperen\Downloads\final_annotations_Canada\Canada\EagqdVXXkAEO4ZZ.jpg</path>
	<source>
		<database>Unknown</database>
	</source>
	<size>
		<width>1200</width>
		<height>900</height>
		<depth>3</depth>
	</size>
	<segmented>0</segmented>
	<object>
		<name>no mask</name>
		<pose>Unspecified</pose>
		<truncated>0</truncated>
		<difficult>0</difficult>
		<bndbox>
			<xmin>789</xmin>
			<ymin>381</ymin>
			<xmax>840</xmax>
			<ymax>454</ymax>
		</bndbox>
	</object>
	<object>
		<name>no mask</name>
		<pose>Unspecified</pose>
		<truncated>0</truncated>
		<difficult>0</difficult>
		<bndbox>
			<xmin>691</xmin>
			<ymin>327</ymin>
			<xmax>710</xmax>
			<ymax>348</ymax>
		</bndbox>
	</object>
	<object>
		<name>no mask</name>
		<pose>Unspecified</pose>
		<truncated>0</truncated>
		<difficult>0</difficult>
		<bndbox>
			<xmin>723</xmin>
			<ymin>339</ymin>
			<xmax>739</xmax>
			<ymax>357</ymax>
		</bndbox>
	</object>
	<object>
		<name>no mask</name>
		<pose>Unspecified</pose>
		<truncated>0</truncated>
		<difficult>0</difficult>
		<bndbox>
			<xmin>643</xmin>
			<ymin>326</ymin>
			<xmax>665</xmax>
			<ymax>353</ymax>
		</bndbox>
	</object>
	<object>
		<name>no mask</name>
		<pose>Unspecified</pose>
		<truncated>0</truncated>
		<difficult>0</difficult>
		<bndbox>
			<xmin>593</xmin>
			<ymin>346</ymin>
			<xmax>615</xmax>
			<ymax>370</ymax>
		</bndbox>
	</object>
	<object>
		<name>no mask</name>
		<pose>Unspecified</pose>
		<truncated>0</truncated>
		<difficult>0</difficult>
		<bndbox>
			<xmin>547</xmin>
			<ymin>318</ymin>
			<xmax>568</xmax>
			<ymax>346</ymax>
		</bndbox>
	</object>
	<object>
		<name>no mask</name>
		<pose>Unspecified</pose>
		<truncated>0</truncated>
		<difficult>0</difficult>
		<bndbox>
			<xmin>492</xmin>
			<ymin>326</ymin>
			<xmax>511</xmax>
			<ymax>354</ymax>
		</bndbox>
	</object>
	<object>
		<name>no mask</name>
		<pose>Unspecified</pose>
		<truncated>0</truncated>
		<difficult>1</difficult>
		<bndbox>
			<xmin>405</xmin>
			<ymin>335</ymin>
			<xmax>421</xmax>
			<ymax>353</ymax>
		</bndbox>
	</object>
	<object>
		<name>no mask</name>
		<pose>Unspecified</pose>
		<truncated>0</truncated>
		<difficult>0</difficult>
		<bndbox>
			<xmin>239</xmin>
			<ymin>309</ymin>
			<xmax>262</xmax>
			<ymax>334</ymax>
		</bndbox>
	</object>
</annotation>
