<annotation verified="yes">
	<folder>indian_images</folder>
	<filename>EaO6pUDWkAUs3na.jpg</filename>
	<path>C:\Users\Alperen\Desktop\qatar_new_dataset\indian_images\EaO6pUDWkAUs3na.jpg</path>
	<source>
		<database>Unknown</database>
	</source>
	<size>
		<width>1193</width>
		<height>1200</height>
		<depth>3</depth>
	</size>
	<segmented>0</segmented>
	<object>
		<name>mask</name>
		<pose>Unspecified</pose>
		<truncated>0</truncated>
		<difficult>0</difficult>
		<bndbox>
			<xmin>656</xmin>
			<ymin>273</ymin>
			<xmax>748</xmax>
			<ymax>363</ymax>
		</bndbox>
	</object>
	<object>
		<name>no mask</name>
		<pose>Unspecified</pose>
		<truncated>0</truncated>
		<difficult>0</difficult>
		<bndbox>
			<xmin>364</xmin>
			<ymin>162</ymin>
			<xmax>463</xmax>
			<ymax>267</ymax>
		</bndbox>
	</object>
	<object>
		<name>mask</name>
		<pose>Unspecified</pose>
		<truncated>0</truncated>
		<difficult>0</difficult>
		<bndbox>
			<xmin>1086</xmin>
			<ymin>131</ymin>
			<xmax>1146</xmax>
			<ymax>213</ymax>
		</bndbox>
	</object>
	<object>
		<name>mask</name>
		<pose>Unspecified</pose>
		<truncated>0</truncated>
		<difficult>0</difficult>
		<bndbox>
			<xmin>939</xmin>
			<ymin>232</ymin>
			<xmax>990</xmax>
			<ymax>301</ymax>
		</bndbox>
	</object>
</annotation>
