<annotation>
	<folder>indian_images</folder>
	<filename>EaOTVeSVAAAonHR.jpg</filename>
	<path>C:\Users\Alperen\Desktop\qatar_new_dataset\indian_images\EaOTVeSVAAAonHR.jpg</path>
	<source>
		<database>Unknown</database>
	</source>
	<size>
		<width>1200</width>
		<height>900</height>
		<depth>3</depth>
	</size>
	<segmented>0</segmented>
	<object>
		<name>mask</name>
		<pose>Unspecified</pose>
		<truncated>0</truncated>
		<difficult>0</difficult>
		<bndbox>
			<xmin>898</xmin>
			<ymin>299</ymin>
			<xmax>985</xmax>
			<ymax>433</ymax>
		</bndbox>
	</object>
	<object>
		<name>mask</name>
		<pose>Unspecified</pose>
		<truncated>0</truncated>
		<difficult>0</difficult>
		<bndbox>
			<xmin>414</xmin>
			<ymin>312</ymin>
			<xmax>492</xmax>
			<ymax>418</ymax>
		</bndbox>
	</object>
	<object>
		<name>mask</name>
		<pose>Unspecified</pose>
		<truncated>0</truncated>
		<difficult>0</difficult>
		<bndbox>
			<xmin>273</xmin>
			<ymin>225</ymin>
			<xmax>373</xmax>
			<ymax>369</ymax>
		</bndbox>
	</object>
	<object>
		<name>mask</name>
		<pose>Unspecified</pose>
		<truncated>0</truncated>
		<difficult>0</difficult>
		<bndbox>
			<xmin>811</xmin>
			<ymin>337</ymin>
			<xmax>874</xmax>
			<ymax>418</ymax>
		</bndbox>
	</object>
	<object>
		<name>mask</name>
		<pose>Unspecified</pose>
		<truncated>0</truncated>
		<difficult>0</difficult>
		<bndbox>
			<xmin>501</xmin>
			<ymin>247</ymin>
			<xmax>555</xmax>
			<ymax>325</ymax>
		</bndbox>
	</object>
	<object>
		<name>mask</name>
		<pose>Unspecified</pose>
		<truncated>0</truncated>
		<difficult>0</difficult>
		<bndbox>
			<xmin>657</xmin>
			<ymin>273</ymin>
			<xmax>741</xmax>
			<ymax>390</ymax>
		</bndbox>
	</object>
</annotation>
